docs/source/conf.py
mwrpy/__init__.py
mwrpy/atmos.py
mwrpy/cli.py
mwrpy/constants.py
mwrpy/exceptions.py
mwrpy/process_mwrpy.py
mwrpy/py.typed
mwrpy/rpg_mwr.py
mwrpy/utils.py
mwrpy/version.py
mwrpy/level1/__init__.py
mwrpy/level1/droplet_mwrpy.py
mwrpy/level1/lev1_meta_nc.py
mwrpy/level1/met_quality_control.py
mwrpy/level1/quality_control.py
mwrpy/level1/rpg_bin.py
mwrpy/level1/write_lev1_nc.py
mwrpy/level2/__init__.py
mwrpy/level2/get_ret_coeff.py
mwrpy/level2/lev2_collocated.py
mwrpy/level2/lev2_meta_nc.py
mwrpy/level2/lwp_offset.py
mwrpy/level2/write_lev2_nc.py
mwrpy/plots/__init__.py
mwrpy/plots/generate_plots.py
mwrpy/plots/plot_meta.py
mwrpy/plots/plot_utils.py
mwrpy/site_config/hatpro.yaml
mwrpy/site_config/lhatpro.yaml
mwrpy/site_config/lhumpro_u90.yaml
mwrpy/site_config/hyytiala/config.yaml
mwrpy/site_config/hyytiala/coefficients/HPT_NN_FI_Hyytiala_v110_v00110_n01.00.ret
mwrpy/site_config/hyytiala/coefficients/IWV_NN_MA_FI_Hyytiala_v110_v00110_n01.00.ret
mwrpy/site_config/hyytiala/coefficients/LWP_NN_MA_FI_Hyytiala_v110_v00110_n01.00.ret
mwrpy/site_config/hyytiala/coefficients/SPC_NN_MA_FI_Hyytiala_v110_v00110_n01.00.ret
mwrpy/site_config/hyytiala/coefficients/TPB_NN_FI_Hyytiala_v110_v00110_n01.00.ret
mwrpy/site_config/hyytiala/coefficients/TPT_NN_FI_Hyytiala_v110_v00110_n01.00.ret
mwrpy/site_config/juelich/config.yaml
mwrpy/site_config/juelich/coefficients/hpt_deb_rt00_90.nc
mwrpy/site_config/juelich/coefficients/iwv_deb_rt00_90.nc
mwrpy/site_config/juelich/coefficients/lwp_deb_rt00_90.nc
mwrpy/site_config/juelich/coefficients/tbx_deb_rt00_90_00.nc
mwrpy/site_config/juelich/coefficients/tbx_deb_rt00_90_01.nc
mwrpy/site_config/juelich/coefficients/tbx_deb_rt00_90_02.nc
mwrpy/site_config/juelich/coefficients/tbx_deb_rt00_90_03.nc
mwrpy/site_config/juelich/coefficients/tbx_deb_rt00_90_04.nc
mwrpy/site_config/juelich/coefficients/tbx_deb_rt00_90_05.nc
mwrpy/site_config/juelich/coefficients/tbx_deb_rt00_90_06.nc
mwrpy-1.4.1.dist-info/licenses/LICENSE
mwrpy-1.4.1.dist-info/METADATA
mwrpy-1.4.1.dist-info/WHEEL
mwrpy-1.4.1.dist-info/top_level.txt
mwrpy-1.4.1.dist-info/RECORD
