Metadata-Version: 2.4
Name: mwrpy
Version: 1.4.1
Summary: Python package for Microwave Radiometer processing in ACTRIS
Author-email: University of Cologne <actris-ccres-mwr@uni-koeln.de>
License: MIT License
Project-URL: Homepage, https://github.com/actris-cloudnet/mwrpy
Project-URL: Documentation, https://actris-cloudnet.github.io/mwrpy/
Project-URL: Repository, https://github.com/actris-cloudnet/mwrpy
Project-URL: Changelog, https://github.com/actris-cloudnet/mwrpy/blob/main/CHANGELOG.md
Classifier: Development Status :: 3 - Alpha
Classifier: Intended Audience :: Science/Research
Classifier: License :: OSI Approved :: MIT License
Classifier: Programming Language :: Python :: 3.10
Classifier: Programming Language :: Python :: 3.11
Classifier: Topic :: Scientific/Engineering
Requires-Python: >=3.10
License-File: LICENSE
Requires-Dist: matplotlib
Requires-Dist: metpy
Requires-Dist: netCDF4
Requires-Dist: pandas
Requires-Dist: pytz
Requires-Dist: pyyaml
Requires-Dist: scipy
Requires-Dist: suncalc
Requires-Dist: timezonefinder
Provides-Extra: test
Requires-Dist: mypy; extra == "test"
Requires-Dist: pre-commit; extra == "test"
Requires-Dist: pytest; extra == "test"
Requires-Dist: pytest-flakefinder; extra == "test"
Requires-Dist: types-PyYAML; extra == "test"
Requires-Dist: types-pytz; extra == "test"
Provides-Extra: dev
Requires-Dist: release-version; extra == "dev"
Dynamic: license-file
